safety/VERSION
safety/__init__.py
safety/__main__.py
safety/cli.py
safety/cli_util.py
safety/cli_utils.py
safety/console.py
safety/constants.py
safety/errors.py
safety/formatter.py
safety/models.py
safety/output_utils.py
safety/safety-policy-template.yml
safety/safety.py
safety/util.py
safety/alerts/__init__.py
safety/alerts/github.py
safety/alerts/requirements.py
safety/alerts/utils.py
safety/alerts/templates/issue.jinja2
safety/alerts/templates/pr.jinja2
safety/auth/__init__.py
safety/auth/cli.py
safety/auth/cli_utils.py
safety/auth/constants.py
safety/auth/main.py
safety/auth/models.py
safety/auth/server.py
safety/auth/utils.py
safety/formatters/__init__.py
safety/formatters/bare.py
safety/formatters/html.py
safety/formatters/json.py
safety/formatters/screen.py
safety/formatters/text.py
safety/formatters/schemas/__init__.py
safety/formatters/schemas/common.py
safety/formatters/schemas/v0_5.py
safety/formatters/schemas/v3_0.py
safety/formatters/schemas/zero_five.py
safety/scan/__init__.py
safety/scan/command.py
safety/scan/constants.py
safety/scan/decorators.py
safety/scan/main.py
safety/scan/models.py
safety/scan/render.py
safety/scan/util.py
safety/scan/validators.py
safety/scan/ecosystems/__init__.py
safety/scan/ecosystems/base.py
safety/scan/ecosystems/target.py
safety/scan/ecosystems/python/__init__.py
safety/scan/ecosystems/python/dependencies.py
safety/scan/ecosystems/python/main.py
safety/scan/finder/__init__.py
safety/scan/finder/file_finder.py
safety/scan/finder/handlers.py
safety/templates/.DS_Store
safety/templates/index.html
safety/templates/scan/index.html
safety-3.2.11.dist-info/LICENSE
safety-3.2.11.dist-info/LICENSES.md
safety-3.2.11.dist-info/METADATA
safety-3.2.11.dist-info/WHEEL
safety-3.2.11.dist-info/entry_points.txt
safety-3.2.11.dist-info/top_level.txt
safety-3.2.11.dist-info/RECORD
