Metadata-Version: 2.1
Name: safety
Version: 3.2.11
Summary: Checks installed dependencies for known vulnerabilities and licenses.
Home-page: https://github.com/pyupio/safety
Author: safetycli.com
Author-email: support@safetycli.com
License: MIT license
Project-URL: Bug Tracker, https://github.com/pyupio/safety/issues
Project-URL: Source, https://github.com/pyupio/safety/
Project-URL: Documentation, https://docs.pyup.io/docs/getting-started-with-safety-cli
Keywords: safety,vulnerabilities,dependencies,licenses,check
Classifier: Development Status :: 5 - Production/Stable
Classifier: Intended Audience :: Developers
Classifier: License :: OSI Approved :: MIT License
Classifier: Natural Language :: English
Classifier: Operating System :: POSIX :: Linux
Classifier: Operating System :: MacOS
Classifier: Operating System :: Microsoft :: Windows
Classifier: Programming Language :: Python :: 3 :: Only
Classifier: Programming Language :: Python :: 3.6
Classifier: Programming Language :: Python :: 3.7
Classifier: Programming Language :: Python :: 3.8
Classifier: Programming Language :: Python :: 3.9
Classifier: Programming Language :: Python :: 3.10
Classifier: Programming Language :: Python :: 3.11
Requires-Python: >=3.7
License-File: LICENSE
License-File: LICENSES.md
Requires-Dist: setuptools>=65.5.1
Requires-Dist: Click>=8.0.2
Requires-Dist: urllib3>=1.26.5
Requires-Dist: requests
Requires-Dist: packaging>=21.0
Requires-Dist: dparse>=0.6.4
Requires-Dist: ruamel.yaml>=0.17.21
Requires-Dist: jinja2>=3.1.0
Requires-Dist: marshmallow>=3.15.0
Requires-Dist: Authlib>=1.2.0
Requires-Dist: rich
Requires-Dist: typer
Requires-Dist: pydantic>=1.10.12
Requires-Dist: safety_schemas>=0.0.8
Requires-Dist: typing-extensions>=4.7.1
Requires-Dist: filelock~=3.12.2
Requires-Dist: psutil~=6.0.0
Provides-Extra: github
Requires-Dist: pygithub>=1.43.3; extra == "github"
Provides-Extra: gitlab
Requires-Dist: python-gitlab>=1.3.0; extra == "gitlab"
Provides-Extra: spdx
Requires-Dist: spdx-tools>=0.8.2; extra == "spdx"
